LICENSE.txt
README.rst
setup.py
undervolt.py
undervolt.egg-info/PKG-INFO
undervolt.egg-info/SOURCES.txt
undervolt.egg-info/dependency_links.txt
undervolt.egg-info/entry_points.txt
undervolt.egg-info/top_level.txt