Metadata-Version: 2.1
Name: undervolt
Version: 0.4.0
Summary: Undervolt Intel CPUs under Linux
Home-page: http://github.com/georgewhewell/undervolt
Author: George Whewell
Author-email: georgerw@gmail.com
License: GPL
Keywords: undervolt,intel,linux
Classifier: Development Status :: 3 - Alpha
Classifier: License :: OSI Approved :: GNU General Public License (GPL)
Classifier: Programming Language :: Python :: 2
Classifier: Programming Language :: Python :: 3
License-File: LICENSE.txt
